{
   "AccessConditions":[""],
   "AccessStatus":["Open"],
   "BarCode":["1232423467"],
   "CatalogueStatus":["Catalogued"],
   "Category":[""],
   "ClosedUntil":[""],
   "Condition":[""],
   "ConservationPriority":[""],
   "Created":["11/10/2018"],
   "Creator":["admin"],
   "CurrentLocation":[""],
   "Date":[""],
   "Description":["Creating a new parent with reference P DAB"],
   "Extent":["2.13 linear meters"],
   "Format":[""],
   "Level":["Collection"],
   "URL":[""],
   "Modified":["11/10/2018"],
   "Modifier":["admin"],
   "NormalLocation":[""],
   "PhysicalDescription":[""],
   "RCN":["R12"],
   "RecordID":["2253ce08-7106-43ba-857f-eac0c86b0021"],
   "RefNo":["Q DAB"],
   "RelatedMaterial":[""],
   "Repository":["Museum"],
   "Title":["A 2nd new collection"
   ]
}
